Workbook

Sheet Instructions
A1: NewFinera — 3-Statement Model Template
A2: Fill in once per client; P&L, Balance Sheet, Cash Flow and Dashboard calculate automatically.
A4: 1. Client Finance Officer brief
A5: Run docs/templates/client-finance-officer-brief.md first — this model assumes that intake is done.
A7: 2. Fill the Trial Balance Input tab
A8: Enter the client's name, reporting period, entity type and GST basis (dropdowns in row 6), and every trial balance line (up to 200 accounts, rows 8–207) with its Category from the dropdown and Prior/Current period closing balances. Column E flags any row whose category is missing or misspelled — those rows are left out of every statement until fixed. Blue cells are the only ones to edit.
A10: 3. Check the tie-outs
A11: Balance Sheet tab: Total Assets must equal Total Liabilities + Equity (both periods). Cash Flow tab: the computed closing cash must equal the Balance Sheet’s actual Cash balance. Both are automatic checks — if either shows an exception, the trial balance categorisation needs review before delivery.
A13: 4. Read off P&L, Balance Sheet, Cash Flow
A14: Each tab is fully formula-driven from the Input tab — nothing else to fill in.
A16: 5. Feed the Dashboard
A17: The Dashboard tab mirrors the KPIs the React dashboard product (product/dashboard/) shows a client — use its figures when populating that dashboard’s *Card.tsx sample-data files with real numbers.
... A23: This model is prep-only, same as every other tool in this repo: it never lodges or files anything. Verify current AASB 1060 / GST / reporting-threshold treatment per docs/REPORTING-STANDARDS.md before relying on any figure for a real client filing.

Sheet Trial Balance Input
A1: Trial Balance Input
A2: Blue cells only. One row per account. Category drives every downstream formula.
A3: Rows needing a category | B3: =COUNTIF($E$8:$E$207,"CHECK CATEGORY") -> 0 | C3: =IF(B3=0,"All rows categorised","Fix the rows marked CHECK CATEGORY in column E") -> All rows categorised
A4: Client Business Name | B4: [Example Trading Co Pty Ltd] | C4: Current Period | D4: FY2026 (1 Jul 2025 – 30 Jun 2026)
A5: Retained Earnings — opening balance, start of PRIOR period | C5: 25000 | D5: single figure — not a repeating TB line
A6: Entity type | B6: Company | C6: GST basis | D6: Accruals
A7: Account Name | B7: Category | C7: Prior Period ($) | D7: Current Period ($) | E7: Category check | G7: Valid categories (exact spelling)
A8: Sales Revenue | B8: Revenue | C8: 380000 | D8: 450000 | E8: =IF(AND(A8&""="",B8&""="",N(C8)=0,N(D8)=0),"",IF(COUNTIF($G$8:$G$20,B8&"")>0,"OK","CHECK CATEGORY")) -> OK | G8: Revenue
A9: Cost of Goods Sold | B9: COGS | C9: 190000 | D9: 220000 | E9: =IF(AND(A9&""="",B9&""="",N(C9)=0,N(D9)=0),"",IF(COUNTIF($G$8:$G$20,B9&"")>0,"OK","CHECK CATEGORY")) -> OK | G9: COGS
A10: Rent | B10: Operating Expenses | C10: 24000 | D10: 24000 | E10: =IF(AND(A10&""="",B10&""="",N(C10)=0,N(D10)=0),"",IF(COUNTIF($G$8:$G$20,B10&"")>0,"OK","CHECK CATEGORY")) -> OK | G10: Operating Expenses
A11: Wages & Salaries | B11: Operating Expenses | C11: 90000 | D11: 105000 | E11: =IF(AND(A11&""="",B11&""="",N(C11)=0,N(D11)=0),"",IF(COUNTIF($G$8:$G$20,B11&"")>0,"OK","CHECK CATEGORY")) -> OK | G11: Depreciation & Amortisation
A12: Marketing & Advertising | B12: Operating Expenses | C12: 15000 | D12: 20000 | E12: =IF(AND(A12&""="",B12&""="",N(C12)=0,N(D12)=0),"",IF(COUNTIF($G$8:$G$20,B12&"")>0,"OK","CHECK CATEGORY")) -> OK | G12: Interest Expense
A13: Utilities | B13: Operating Expenses | C13: 6000 | D13: 6500 | E13: =IF(AND(A13&""="",B13&""="",N(C13)=0,N(D13)=0),"",IF(COUNTIF($G$8:$G$20,B13&"")>0,"OK","CHECK CATEGORY")) -> OK | G13: Tax Expense
A14: Insurance | B14: Operating Expenses | C14: 4000 | D14: 4200 | E14: =IF(AND(A14&""="",B14&""="",N(C14)=0,N(D14)=0),"",IF(COUNTIF($G$8:$G$20,B14&"")>0,"OK","CHECK CATEGORY")) -> OK | G14: Cash
A15: Office Supplies | B15: Operating Expenses | C15: 3000 | D15: 3300 | E15: =IF(AND(A15&""="",B15&""="",N(C15)=0,N(D15)=0),"",IF(COUNTIF($G$8:$G$20,B15&"")>0,"OK","CHECK CATEGORY")) -> OK | G15: Other Current Assets
A16: Depreciation Expense | B16: Depreciation & Amortisation | C16: 12000 | D16: 14000 | E16: =IF(AND(A16&""="",B16&""="",N(C16)=0,N(D16)=0),"",IF(COUNTIF($G$8:$G$20,B16&"")>0,"OK","CHECK CATEGORY")) -> OK | G16: Non-Current Assets
A17: Interest on Loan | B17: Interest Expense | C17: 5000 | D17: 4500 | E17: =IF(AND(A17&""="",B17&""="",N(C17)=0,N(D17)=0),"",IF(COUNTIF($G$8:$G$20,B17&"")>0,"OK","CHECK CATEGORY")) -> OK | G17: Current Liabilities
A18: Income Tax Expense | B18: Tax Expense | C18: 8000 | D18: 12000 | E18: =IF(AND(A18&""="",B18&""="",N(C18)=0,N(D18)=0),"",IF(COUNTIF($G$8:$G$20,B18&"")>0,"OK","CHECK CATEGORY")) -> OK | G18: Non-Current Liabilities
A19: Cash at Bank | B19: Cash | C19: 48000 | D19: 39000 | E19: =IF(AND(A19&""="",B19&""="",N(C19)=0,N(D19)=0),"",IF(COUNTIF($G$8:$G$20,B19&"")>0,"OK","CHECK CATEGORY")) -> OK | G19: Share Capital
A20: Trade Receivables | B20: Other Current Assets | C20: 28000 | D20: 34000 | E20: =IF(AND(A20&""="",B20&""="",N(C20)=0,N(D20)=0),"",IF(COUNTIF($G$8:$G$20,B20&"")>0,"OK","CHECK CATEGORY")) -> OK | G20: Drawings/Dividends Paid
A21: Inventory | B21: Other Current Assets | C21: 45000 | D21: 52000 | E21: =IF(AND(A21&""="",B21&""="",N(C21)=0,N(D21)=0),"",IF(COUNTIF($G$8:$G$20,B21&"")>0,"OK","CHECK CATEGORY")) -> OK
A22: Equipment & Fixtures (net) | B22: Non-Current Assets | C22: 60000 | D22: 70000 | E22: =IF(AND(A22&""="",B22&""="",N(C22)=0,N(D22)=0),"",IF(COUNTIF($G$8:$G$20,B22&"")>0,"OK","CHECK CATEGORY")) -> OK
A23: Trade Payables | B23: Current Liabilities | C23: 22000 | D23: 26000 | E23: =IF(AND(A23&""="",B23&""="",N(C23)=0,N(D23)=0),"",IF(COUNTIF($G$8:$G$20,B23&"")>0,"OK","CHECK CATEGORY")) -> OK
A24: GST Payable | B24: Current Liabilities | C24: 6000 | D24: 7500 | E24: =IF(AND(A24&""="",B24&""="",N(C24)=0,N(D24)=0),"",IF(COUNTIF($G$8:$G$20,B24&"")>0,"OK","CHECK CATEGORY")) -> OK
A25: Bank Loan (long-term) | B25: Non-Current Liabilities | C25: 70000 | D25: 60000 | E25: =IF(AND(A25&""="",B25&""="",N(C25)=0,N(D25)=0),"",IF(COUNTIF($G$8:$G$20,B25&"")>0,"OK","CHECK CATEGORY")) -> OK
A26: Share Capital (paid-up) | B26: Share Capital | C26: 50000 | D26: 50000 | E26: =IF(AND(A26&""="",B26&""="",N(C26)=0,N(D26)=0),"",IF(COUNTIF($G$8:$G$20,B26&"")>0,"OK","CHECK CATEGORY")) -> OK
A27: Dividends Paid | B27: Drawings/Dividends Paid | C27: 15000 | D27: 18000 | E27: =IF(AND(A27&""="",B27&""="",N(C27)=0,N(D27)=0),"",IF(COUNTIF($G$8:$G$20,B27&"")>0,"OK","CHECK CATEGORY")) -> OK
E28: =IF(AND(A28&""="",B28&""="",N(C28)=0,N(D28)=0),"",IF(COUNTIF($G$8:$G$20,B28&"")>0,"OK","CHECK CATEGORY"))
E29: =IF(AND(A29&""="",B29&""="",N(C29)=0,N(D29)=0),"",IF(COUNTIF($G$8:$G$20,B29&"")>0,"OK","CHECK CATEGORY"))
E30: =IF(AND(A30&""="",B30&""="",N(C30)=0,N(D30)=0),"",IF(COUNTIF($G$8:$G$20,B30&"")>0,"OK","CHECK CATEGORY"))
E31: =IF(AND(A31&""="",B31&""="",N(C31)=0,N(D31)=0),"",IF(COUNTIF($G$8:$G$20,B31&"")>0,"OK","CHECK CATEGORY"))
E32: =IF(AND(A32&""="",B32&""="",N(C32)=0,N(D32)=0),"",IF(COUNTIF($G$8:$G$20,B32&"")>0,"OK","CHECK CATEGORY"))
E33: =IF(AND(A33&""="",B33&""="",N(C33)=0,N(D33)=0),"",IF(COUNTIF($G$8:$G$20,B33&"")>0,"OK","CHECK CATEGORY"))
E34: =IF(AND(A34&""="",B34&""="",N(C34)=0,N(D34)=0),"",IF(COUNTIF($G$8:$G$20,B34&"")>0,"OK","CHECK CATEGORY"))
E35: =IF(AND(A35&""="",B35&""="",N(C35)=0,N(D35)=0),"",IF(COUNTIF($G$8:$G$20,B35&"")>0,"OK","CHECK CATEGORY"))
E36: =IF(AND(A36&""="",B36&""="",N(C36)=0,N(D36)=0),"",IF(COUNTIF($G$8:$G$20,B36&"")>0,"OK","CHECK CATEGORY"))
E37: =IF(AND(A37&""="",B37&""="",N(C37)=0,N(D37)=0),"",IF(COUNTIF($G$8:$G$20,B37&"")>0,"OK","CHECK CATEGORY"))
E38: =IF(AND(A38&""="",B38&""="",N(C38)=0,N(D38)=0),"",IF(COUNTIF($G$8:$G$20,B38&"")>0,"OK","CHECK CATEGORY"))
E39: =IF(AND(A39&""="",B39&""="",N(C39)=0,N(D39)=0),"",IF(COUNTIF($G$8:$G$20,B39&"")>0,"OK","CHECK CATEGORY"))
... E207: =IF(AND(A207&""="",B207&""="",N(C207)=0,N(D207)=0),"",IF(COUNTIF($G$8:$G$20,B207&"")>0,"OK","CHECK CATEGORY"))

Sheet P&L
A1: Profit & Loss
A2: [Example Trading Co Pty Ltd] — formula-driven from Trial Balance Input
B4: Prior Period | C4: Current Period | D4: Variance
A5: Revenue | B5: =SUMIF('Trial Balance Input'!$B$8:$B$207,"Revenue",'Trial Balance Input'!$C$8:$C$207) -> 380000 | C5: =SUMIF('Trial Balance Input'!$B$8:$B$207,"Revenue",'Trial Balance Input'!$D$8:$D$207) -> 450000
A6: less Cost of Goods Sold | B6: =SUMIF('Trial Balance Input'!$B$8:$B$207,"COGS",'Trial Balance Input'!$C$8:$C$207) -> 190000 | C6: =SUMIF('Trial Balance Input'!$B$8:$B$207,"COGS",'Trial Balance Input'!$D$8:$D$207) -> 220000
A7: Gross Profit | B7: =B5-B6 -> 190000 | C7: =C5-C6 -> 230000 | D7: =IFERROR((C7-B7)/ABS(B7),"-") -> 0.21052632
A9: less Operating Expenses | B9: =SUMIF('Trial Balance Input'!$B$8:$B$207,"Operating Expenses",'Trial Balance Input'!$C$8:$C$207) -> 142000 | C9: =SUMIF('Trial Balance Input'!$B$8:$B$207,"Operating Expenses",'Trial Balance Input'!$D$8:$D$207) -> 163000
A10: less Depreciation & Amortisation | B10: =SUMIF('Trial Balance Input'!$B$8:$B$207,"Depreciation & Amortisation",'Trial Balance Input'!$C$8:$C$207) -> 12000 | C10: =SUMIF('Trial Balance Input'!$B$8:$B$207,"Depreciation & Amortisation",'Trial Balance Input'!$D$8:$D$207) -> 14000
A11: EBIT | B11: =B7-B9-B10 -> 36000 | C11: =C7-C9-C10 -> 53000 | D11: =IFERROR((C11-B11)/ABS(B11),"-") -> 0.47222222
A13: less Interest Expense | B13: =SUMIF('Trial Balance Input'!$B$8:$B$207,"Interest Expense",'Trial Balance Input'!$C$8:$C$207) -> 5000 | C13: =SUMIF('Trial Balance Input'!$B$8:$B$207,"Interest Expense",'Trial Balance Input'!$D$8:$D$207) -> 4500
A14: Profit before tax | B14: =B11-B13 -> 31000 | C14: =C11-C13 -> 48500 | D14: =IFERROR((C14-B14)/ABS(B14),"-") -> 0.56451613
A16: less Tax Expense | B16: =SUMIF('Trial Balance Input'!$B$8:$B$207,"Tax Expense",'Trial Balance Input'!$C$8:$C$207) -> 8000 | C16: =SUMIF('Trial Balance Input'!$B$8:$B$207,"Tax Expense",'Trial Balance Input'!$D$8:$D$207) -> 12000
A17: Net Profit | B17: =B14-B16 -> 23000 | C17: =C14-C16 -> 36500 | D17: =IFERROR((C17-B17)/ABS(B17),"-") -> 0.58695652
A20: Gross Margin % | B20: =IFERROR(B7/B5,"-") -> 0.5 | C20: =IFERROR(C7/C5,"-") -> 0.51111111
A21: Net Margin % | B21: =IFERROR(B17/B5,"-") -> 0.060526316 | C21: =IFERROR(C17/C5,"-") -> 0.081111111

Sheet Balance Sheet
A1: Balance Sheet
A2: [Example Trading Co Pty Ltd] — formula-driven from Trial Balance Input and P&L
B4: Prior Period | C4: Current Period
A5: ASSETS
A6: Cash | B6: =SUMIF('Trial Balance Input'!$B$8:$B$207,"Cash",'Trial Balance Input'!$C$8:$C$207) -> 48000 | C6: =SUMIF('Trial Balance Input'!$B$8:$B$207,"Cash",'Trial Balance Input'!$D$8:$D$207) -> 39000
A7: Other Current Assets (receivables, inventory, etc.) | B7: =SUMIF('Trial Balance Input'!$B$8:$B$207,"Other Current Assets",'Trial Balance Input'!$C$8:$C$207) -> 73000 | C7: =SUMIF('Trial Balance Input'!$B$8:$B$207,"Other Current Assets",'Trial Balance Input'!$D$8:$D$207) -> 86000
A8: Total Current Assets | B8: =B6+B7 -> 121000 | C8: =C6+C7 -> 125000
A9: Non-Current Assets | B9: =SUMIF('Trial Balance Input'!$B$8:$B$207,"Non-Current Assets",'Trial Balance Input'!$C$8:$C$207) -> 60000 | C9: =SUMIF('Trial Balance Input'!$B$8:$B$207,"Non-Current Assets",'Trial Balance Input'!$D$8:$D$207) -> 70000
A10: TOTAL ASSETS | B10: =B8+B9 -> 181000 | C10: =C8+C9 -> 195000
A12: LIABILITIES
A13: Current Liabilities | B13: =SUMIF('Trial Balance Input'!$B$8:$B$207,"Current Liabilities",'Trial Balance Input'!$C$8:$C$207) -> 28000 | C13: =SUMIF('Trial Balance Input'!$B$8:$B$207,"Current Liabilities",'Trial Balance Input'!$D$8:$D$207) -> 33500
A14: Non-Current Liabilities | B14: =SUMIF('Trial Balance Input'!$B$8:$B$207,"Non-Current Liabilities",'Trial Balance Input'!$C$8:$C$207) -> 70000 | C14: =SUMIF('Trial Balance Input'!$B$8:$B$207,"Non-Current Liabilities",'Trial Balance Input'!$D$8:$D$207) -> 60000
A15: TOTAL LIABILITIES | B15: =B13+B14 -> 98000 | C15: =C13+C14 -> 93500
A17: EQUITY
A18: =IF('Trial Balance Input'!$B$6="Company"," Share Capital"," Owner's Capital") -> Share Capital | B18: =SUMIF('Trial Balance Input'!$B$8:$B$207,"Share Capital",'Trial Balance Input'!$C$8:$C$207) -> 50000 | C18: =SUMIF('Trial Balance Input'!$B$8:$B$207,"Share Capital",'Trial Balance Input'!$D$8:$D$207) -> 50000
A19: =IF('Trial Balance Input'!$B$6="Company"," (memo) Dividends paid in the period"," (memo) Owner drawings in the period") -> (memo) Dividends paid in the period | B19: =SUMIF('Trial Balance Input'!$B$8:$B$207,"Drawings/Dividends Paid",'Trial Balance Input'!$C$8:$C$207) -> 15000 | C19: =SUMIF('Trial Balance Input'!$B$8:$B$207,"Drawings/Dividends Paid",'Trial Balance Input'!$D$8:$D$207) -> 18000
A20: Retained Earnings (closing) | B20: ='Trial Balance Input'!$C$5+'P&L'!B17-B19 -> 33000 | C20: =B20+'P&L'!C17-C19 -> 51500
A21: TOTAL EQUITY | B21: =B18+B20 -> 83000 | C21: =C18+C20 -> 101500
A23: TOTAL LIABILITIES + EQUITY | B23: =B15+B21 -> 181000 | C23: =C15+C21 -> 195000
A25: Balance check (Assets − Liabilities − Equity) | B25: =B10-B23 -> 0 | C25: =C10-C23 -> 0
A26: =IF(AND(ABS(B25)<1,ABS(C25)<1),"TIES — Assets = Liabilities + Equity, both periods","EXCEPTION — does not balance, review the trial balance categorisation") -> TIES — Assets = Liabilities + Equity, both periods
A27: =IF('Trial Balance Input'!$B$3=0,"All trial balance rows categorised","EXCEPTION — "&'Trial Balance Input'!$B$3&" trial balance row(s) have a missing or misspelled category (Input tab, column E)") -> All trial balance rows categorised
A28: =IF('Trial Balance Input'!$B$6="Company","Company: confirm the Dividends line holds declared dividends only. Money the owner takes out otherwise is a director loan — review Division 7A.","") -> Company: confirm the Dividends line holds declared dividends only. Money the owner takes out otherwise is a director loan — review Division 7A.

Sheet Cash Flow
A1: Cash Flow Statement (indirect method)
A2: [Example Trading Co Pty Ltd] — current period movement, formula-driven from P&L and Balance Sheet
B4: Current Period | C4: Basis
A5: Operating Activities
A6: Net Profit | B6: ='P&L'!C17 -> 36500 | C6: P&L, current period
A7: + Depreciation & Amortisation (non-cash addback) | B7: =SUMIF('Trial Balance Input'!$B$8:$B$207,"Depreciation & Amortisation",'Trial Balance Input'!$D$8:$D$207) -> 14000 | C7: Trial Balance, current period
A8: − Increase in Other Current Assets | B8: =-('Balance Sheet'!C7-'Balance Sheet'!B7) -> -13000 | C8: Balance Sheet movement, Other Current Assets
A9: + Increase in Current Liabilities | B9: ='Balance Sheet'!C13-'Balance Sheet'!B13 -> 5500 | C9: Balance Sheet movement, Current Liabilities
A10: Net Cash from Operating Activities | B10: =SUM(B6:B9) -> 43000
A12: Investing Activities
A13: − Purchase of Non-Current Assets (net capex) | B13: =-(('Balance Sheet'!C9-'Balance Sheet'!B9)+B7) -> -24000 | C13: NCA closing − NCA opening + Depreciation addback (grosses the net BS movement back up to cash capex)
A14: Net Cash from Investing Activities | B14: =B13 -> -24000
A16: Financing Activities
A17: + Increase in Share Capital | B17: ='Balance Sheet'!C18-'Balance Sheet'!B18 -> 0 | C17: Balance Sheet movement, Share Capital
A18: − Drawings / Dividends Paid | B18: =-'Balance Sheet'!C19 -> -18000 | C18: Trial Balance, current period
A19: +/− Movement in Non-Current Liabilities | B19: ='Balance Sheet'!C14-'Balance Sheet'!B14 -> -10000 | C19: Balance Sheet movement, Non-Current Liabilities (e.g. loan drawdown/repayment)
A20: Net Cash from Financing Activities | B20: =SUM(B17:B19) -> -28000
A22: Net Increase/(Decrease) in Cash | B22: =B10+B14+B20 -> -9000
A23: Opening Cash | B23: ='Balance Sheet'!B6 -> 48000 | C23: Balance Sheet, Cash, prior period
A24: Closing Cash (computed) | B24: =B23+B22 -> 39000
A25: Closing Cash (per Balance Sheet) | B25: ='Balance Sheet'!C6 -> 39000 | C25: Balance Sheet, Cash, current period
A27: Tie-out check | B27: =B24-B25 -> 0
A28: =IF(ABS(B27)<1,"TIES — computed closing cash equals the Balance Sheet cash balance","EXCEPTION — does not tie, review the trial balance categorisation") -> TIES — computed closing cash equals the Balance Sheet cash balance

Sheet Dashboard
A1: Dashboard KPIs
A2: [Example Trading Co Pty Ltd] — same metrics the React client dashboard (product/dashboard/) presents
A4: KPI | B4: Prior Period | C4: Current Period | D4: How it’s calculated
A5: Revenue | B5: ='P&L'!B5 -> 380000 | C5: ='P&L'!C5 -> 450000 | D5: P&L
A6: Net Profit | B6: ='P&L'!B17 -> 23000 | C6: ='P&L'!C17 -> 36500 | D6: P&L
A7: Revenue Growth % | B7: n/a | C7: =IFERROR((C5-B5)/ABS(B5),"-") -> 0.18421053 | D7: This period vs prior
A8: Gross Margin % | B8: ='P&L'!B20 -> 0.5 | C8: ='P&L'!C20 -> 0.51111111 | D8: P&L
A9: Net Margin % | B9: ='P&L'!B21 -> 0.060526316 | C9: ='P&L'!C21 -> 0.081111111 | D9: P&L
A10: Current Ratio | B10: =IFERROR('Balance Sheet'!B8/'Balance Sheet'!B13,"-") -> 4.3214286 | C10: =IFERROR('Balance Sheet'!C8/'Balance Sheet'!C13,"-") -> 3.7313433 | D10: Total Current Assets ÷ Current Liabilities
A11: Cash Ratio | B11: =IFERROR('Balance Sheet'!B6/'Balance Sheet'!B13,"-") -> 1.7142857 | C11: =IFERROR('Balance Sheet'!C6/'Balance Sheet'!C13,"-") -> 1.1641791 | D11: Cash ÷ Current Liabilities
A12: Debt-to-Equity | B12: =IFERROR('Balance Sheet'!B15/'Balance Sheet'!B21,"-") -> 1.1807229 | C12: =IFERROR('Balance Sheet'!C15/'Balance Sheet'!C21,"-") -> 0.92118227 | D12: Total Liabilities ÷ Total Equity
A13: Net Cash Movement (current period) | C13: ='Cash Flow'!B22 -> -9000 | D13: Cash Flow statement
A15: These are the same figures to carry into product/dashboard/src/components/dashboard/*Card.tsx when building this client’s real dashboard — see docs/SERVICE-MODEL.md §5 for the tailoring checklist.

Sheet Monthly (optional)
A1: Monthly figures (optional)
A2: Blue cells only. Fill to draw the month-by-month charts on the client web dashboard. Totals must agree to the P&L once all 12 months are in.
A4: Month | B4: Revenue ($) | C4: Net Profit ($) | D4: Cash at month end ($)
A17: Total | B17: =SUM(B5:B16) -> 0 | C17: =SUM(C5:C16) -> 0
A19: Difference to P&L (should be $0) | B19: =IF(COUNT(B5:B16)=12,B17-'P&L'!C5,"-") -> - | C19: =IF(COUNT(C5:C16)=12,C17-'P&L'!C17,"-") -> -
A20: Last month cash vs Balance Sheet (should be $0) | D20: =IF(ISNUMBER(D16),D16-'Balance Sheet'!C6,"-") -> -
